handyio/__init__.py
handyio/io_utils.py
handyio-0.1.1.dist-info/METADATA
handyio-0.1.1.dist-info/WHEEL
handyio-0.1.1.dist-info/top_level.txt
handyio-0.1.1.dist-info/RECORD
