Metadata-Version: 2.4
Name: handyio
Version: 0.1.1
Summary: Handy utilities for saving/loading lists and dicts to txt files
Author-email: Your Name <you@example.com>
License: MIT
Requires-Python: >=3.8
